<annotation>
	<folder>rgb</folder>
	<filename>057.jpg</filename>
	<path>C:\Users\PC\Desktop\concreteCrackSegmentationDataset\rgb\057.jpg</path>
	<source>
		<database>Unknown</database>
	</source>
	<size>
		<width>4032</width>
		<height>3024</height>
		<depth>3</depth>
	</size>
	<segmented>0</segmented>
	<object>
		<name>Cracks</name>
		<pose>Unspecified</pose>
		<truncated>1</truncated>
		<difficult>0</difficult>
		<bndbox>
			<xmin>466</xmin>
			<ymin>1</ymin>
			<xmax>685</xmax>
			<ymax>190</ymax>
		</bndbox>
	</object>
	<object>
		<name>Cracks</name>
		<pose>Unspecified</pose>
		<truncated>0</truncated>
		<difficult>0</difficult>
		<bndbox>
			<xmin>689</xmin>
			<ymin>200</ymin>
			<xmax>918</xmax>
			<ymax>452</ymax>
		</bndbox>
	</object>
	<object>
		<name>Cracks</name>
		<pose>Unspecified</pose>
		<truncated>0</truncated>
		<difficult>0</difficult>
		<bndbox>
			<xmin>913</xmin>
			<ymin>462</ymin>
			<xmax>1094</xmax>
			<ymax>743</ymax>
		</bndbox>
	</object>
	<object>
		<name>Cracks</name>
		<pose>Unspecified</pose>
		<truncated>0</truncated>
		<difficult>0</difficult>
		<bndbox>
			<xmin>1089</xmin>
			<ymin>681</ymin>
			<xmax>1556</xmax>
			<ymax>900</ymax>
		</bndbox>
	</object>
	<object>
		<name>Cracks</name>
		<pose>Unspecified</pose>
		<truncated>0</truncated>
		<difficult>0</difficult>
		<bndbox>
			<xmin>1485</xmin>
			<ymin>928</ymin>
			<xmax>2008</xmax>
			<ymax>1204</ymax>
		</bndbox>
	</object>
	<object>
		<name>Cracks</name>
		<pose>Unspecified</pose>
		<truncated>0</truncated>
		<difficult>0</difficult>
		<bndbox>
			<xmin>2032</xmin>
			<ymin>1195</ymin>
			<xmax>2413</xmax>
			<ymax>1471</ymax>
		</bndbox>
	</object>
	<object>
		<name>Cracks</name>
		<pose>Unspecified</pose>
		<truncated>0</truncated>
		<difficult>0</difficult>
		<bndbox>
			<xmin>2437</xmin>
			<ymin>1452</ymin>
			<xmax>2742</xmax>
			<ymax>1638</ymax>
		</bndbox>
	</object>
	<object>
		<name>Cracks</name>
		<pose>Unspecified</pose>
		<truncated>0</truncated>
		<difficult>0</difficult>
		<bndbox>
			<xmin>2742</xmin>
			<ymin>1638</ymin>
			<xmax>3051</xmax>
			<ymax>1819</ymax>
		</bndbox>
	</object>
	<object>
		<name>Cracks</name>
		<pose>Unspecified</pose>
		<truncated>0</truncated>
		<difficult>0</difficult>
		<bndbox>
			<xmin>3042</xmin>
			<ymin>1781</ymin>
			<xmax>3328</xmax>
			<ymax>2009</ymax>
		</bndbox>
	</object>
	<object>
		<name>Cracks</name>
		<pose>Unspecified</pose>
		<truncated>0</truncated>
		<difficult>0</difficult>
		<bndbox>
			<xmin>3337</xmin>
			<ymin>2004</ymin>
			<xmax>3632</xmax>
			<ymax>2247</ymax>
		</bndbox>
	</object>
	<object>
		<name>Cracks</name>
		<pose>Unspecified</pose>
		<truncated>0</truncated>
		<difficult>0</difficult>
		<bndbox>
			<xmin>3638</xmin>
			<ymin>2210</ymin>
			<xmax>4028</xmax>
			<ymax>2509</ymax>
		</bndbox>
	</object>
	<object>
		<name>Poor Quality</name>
		<pose>Unspecified</pose>
		<truncated>0</truncated>
		<difficult>0</difficult>
		<bndbox>
			<xmin>2147</xmin>
			<ymin>2352</ymin>
			<xmax>2413</xmax>
			<ymax>2547</ymax>
		</bndbox>
	</object>
</annotation>
