<annotation>
	<folder>rgb</folder>
	<filename>530.JPG</filename>
	<path>C:\Users\PC\Desktop\concreteCrackSegmentationDataset\rgb\530.JPG</path>
	<source>
		<database>Unknown</database>
	</source>
	<size>
		<width>4032</width>
		<height>3024</height>
		<depth>3</depth>
	</size>
	<segmented>0</segmented>
	<object>
		<name>Cracks</name>
		<pose>Unspecified</pose>
		<truncated>1</truncated>
		<difficult>0</difficult>
		<bndbox>
			<xmin>1</xmin>
			<ymin>1116</ymin>
			<xmax>914</xmax>
			<ymax>1294</ymax>
		</bndbox>
	</object>
	<object>
		<name>Cracks</name>
		<pose>Unspecified</pose>
		<truncated>0</truncated>
		<difficult>0</difficult>
		<bndbox>
			<xmin>833</xmin>
			<ymin>1308</ymin>
			<xmax>1676</xmax>
			<ymax>1450</ymax>
		</bndbox>
	</object>
	<object>
		<name>Cracks</name>
		<pose>Unspecified</pose>
		<truncated>0</truncated>
		<difficult>0</difficult>
		<bndbox>
			<xmin>1683</xmin>
			<ymin>1436</ymin>
			<xmax>2233</xmax>
			<ymax>1643</ymax>
		</bndbox>
	</object>
	<object>
		<name>Cracks</name>
		<pose>Unspecified</pose>
		<truncated>0</truncated>
		<difficult>0</difficult>
		<bndbox>
			<xmin>2218</xmin>
			<ymin>1465</ymin>
			<xmax>2768</xmax>
			<ymax>1650</ymax>
		</bndbox>
	</object>
	<object>
		<name>Cracks</name>
		<pose>Unspecified</pose>
		<truncated>0</truncated>
		<difficult>0</difficult>
		<bndbox>
			<xmin>2776</xmin>
			<ymin>1265</ymin>
			<xmax>3033</xmax>
			<ymax>1493</ymax>
		</bndbox>
	</object>
	<object>
		<name>Cracks</name>
		<pose>Unspecified</pose>
		<truncated>0</truncated>
		<difficult>0</difficult>
		<bndbox>
			<xmin>3005</xmin>
			<ymin>1322</ymin>
			<xmax>3376</xmax>
			<ymax>1508</ymax>
		</bndbox>
	</object>
	<object>
		<name>Cracks</name>
		<pose>Unspecified</pose>
		<truncated>1</truncated>
		<difficult>0</difficult>
		<bndbox>
			<xmin>3390</xmin>
			<ymin>1429</ymin>
			<xmax>4032</xmax>
			<ymax>1658</ymax>
		</bndbox>
	</object>
</annotation>
